chwrapper/__init__.py
chwrapper/services/__init__.py
chwrapper/services/base.py
chwrapper/services/search.py
chwrapper-0.2.0.dist-info/DESCRIPTION.rst
chwrapper-0.2.0.dist-info/METADATA
chwrapper-0.2.0.dist-info/metadata.json
chwrapper-0.2.0.dist-info/RECORD
chwrapper-0.2.0.dist-info/top_level.txt
chwrapper-0.2.0.dist-info/WHEEL
tests/__init__.py
tests/test_base.py
tests/test_search.py
